{"orig_lga": "LGA_13910", "orig_name": "Hilltops (A)", "orig_state": "NSW", "fetched_at": "2026-03-16T08:46:26.287935+00:00", "destinations": {"LGA_10550": [{"commodity": "Grains", "industry": "grains", "sector": "cropping", "trips_count": 15, "trailer_loads": 207.3600000000001, "tonnes": 5184.0, "tonne_kms": 2066604.5, "tonnes_per_trailer": 25.0, "avg_trip_distance": 350.15387, "avg_trip_duration": 4.024304, "total_trip_distance": 73341.61, "total_trip_duration": 844.1872, "total_freight_value": 2592000.0, "trip_transport_costs": 351567.0, "cst_per_tonne": 68.0, "cst_per_tonne_km": 0.17011826494861498, "co2_tn": 176.35312}], "LGA_10800": [{"commodity": "Barley", "industry": "grains", "sector": "cropping", "trips_count": 6, "trailer_loads": 219.44727, "tonnes": 5486.1743, "tonne_kms": 632728.3, "tonnes_per_trailer": 24.999973, "avg_trip_distance": 116.66553, "avg_trip_duration": 1.296663, "total_trip_distance": 22105.385, "total_trip_duration": 243.6002, "total_freight_value": 1865301.0, "trip_transport_costs": 114095.0, "cst_per_tonne": 21.0, "cst_per_tonne_km": 0.18032234757552437, "co2_tn": 53.542152}, {"commodity": "Wheat", "industry": "grains", "sector": "cropping", "trips_count": 28, "trailer_loads": 859.3229099999999, "tonnes": 21483.068, "tonne_kms": 3417499.8, "tonnes_per_trailer": 24.999992, "avg_trip_distance": 137.44894, "avg_trip_duration": 1.5462718, "total_trip_distance": 117998.836, "total_trip_duration": 1337.026, "total_freight_value": 8808061.0, "trip_transport_costs": 599218.0, "cst_per_tonne": 28.0, "cst_per_tonne_km": 0.17533820613586457, "co2_tn": 289.70892}], "LGA_11400": [], "LGA_11450": [{"commodity": "Grains", "industry": "grains", "sector": "cropping", "trips_count": 21, "trailer_loads": 73.69950000000001, "tonnes": 1842.4872, "tonne_kms": 642681.3, "tonnes_per_trailer": 25.0, "avg_trip_distance": 311.63745, "avg_trip_duration": 3.2838955, "total_trip_distance": 17138.568, "total_trip_duration": 180.53055, "total_freight_value": 921245.0, "trip_transport_costs": 93747.0, "cst_per_tonne": 51.0, "cst_per_tonne_km": 0.14586843800511642, "co2_tn": 50.57909}], "LGA_12350": [{"commodity": "Pigs", "industry": "livestock", "sector": "livestock", "trips_count": 7, "trailer_loads": 132.0, "tonnes": 2376.0, "tonne_kms": 167953.72, "tonnes_per_trailer": 18.0, "avg_trip_distance": 62.8737, "avg_trip_duration": 0.7224353, "total_trip_distance": 7824.4487, "total_trip_duration": 89.75104, "total_freight_value": 8719920.0, "trip_transport_costs": 44801.0, "cst_per_tonne": 19.0, "cst_per_tonne_km": 0.26674389409603444, "co2_tn": 19.6518}, {"commodity": "Sheep", "industry": "livestock", "sector": "livestock", "trips_count": 150, "trailer_loads": 1074.0, "tonnes": 10740.0, "tonne_kms": 850507.8, "tonnes_per_trailer": 10.0, "avg_trip_distance": 80.977875, "avg_trip_duration": 0.9045401, "total_trip_distance": 82056.28, "total_trip_duration": 916.21466, "total_freight_value": 75180000.0, "trip_transport_costs": 423952.0, "cst_per_tonne": 39.0, "cst_per_tonne_km": 0.49846982960547465, "co2_tn": 185.62729}], "LGA_12870": [{"commodity": "Barley", "industry": "grains", "sector": "cropping", "trips_count": 6, "trailer_loads": 100.29789, "tonnes": 2507.4485, "tonne_kms": 631467.0, "tonnes_per_trailer": 25.000008, "avg_trip_distance": 174.16872, "avg_trip_duration": 1.9340321, "total_trip_distance": 18650.285, "total_trip_duration": 204.05992, "total_freight_value": 852532.0, "trip_transport_costs": 98872.0, "cst_per_tonne": 39.0, "cst_per_tonne_km": 0.1565752397573082, "co2_tn": 50.135746}, {"commodity": "Pigs", "industry": "livestock", "sector": "livestock", "trips_count": 8, "trailer_loads": 127.0, "tonnes": 2286.0, "tonne_kms": 811723.7, "tonnes_per_trailer": 18.0, "avg_trip_distance": 260.56137, "avg_trip_duration": 2.765204, "total_trip_distance": 30123.178, "total_trip_duration": 317.70544, "total_freight_value": 8389620.0, "trip_transport_costs": 164909.0, "cst_per_tonne": 72.0, "cst_per_tonne_km": 0.20315853369279793, "co2_tn": 88.61933}], "LGA_12900": [{"commodity": "Pigs", "industry": "livestock", "sector": "livestock", "trips_count": 9, "trailer_loads": 33.0, "tonnes": 594.0, "tonne_kms": 73275.984, "tonnes_per_trailer": 18.0, "avg_trip_distance": 114.20285, "avg_trip_duration": 1.3146148, "total_trip_distance": 3602.4507, "total_trip_duration": 41.594315, "total_freight_value": 2179980.0, "trip_transport_costs": 18554.0, "cst_per_tonne": 31.0, "cst_per_tonne_km": 0.2532086019227289, "co2_tn": 8.726653}, {"commodity": "Small Cattle", "industry": "livestock", "sector": "livestock", "trips_count": 10, "trailer_loads": 50.0, "tonnes": 1000.0, "tonne_kms": 163519.3, "tonnes_per_trailer": 20.0, "avg_trip_distance": 155.99329, "avg_trip_duration": 1.7617117, "total_trip_distance": 7660.8066, "total_trip_duration": 86.45795, "total_freight_value": 2155000.0, "trip_transport_costs": 37128.0, "cst_per_tonne": 37.0, "cst_per_tonne_km": 0.2270562754921414, "co2_tn": 17.73262}, {"commodity": "Sheep", "industry": "livestock", "sector": "livestock", "trips_count": 61, "trailer_loads": 384.0, "tonnes": 3840.0, "tonne_kms": 599377.94, "tonnes_per_trailer": 10.0, "avg_trip_distance": 154.8587, "avg_trip_duration": 1.7697641, "total_trip_distance": 56509.547, "total_trip_duration": 645.8931, "total_freight_value": 26880000.0, "trip_transport_costs": 274726.0, "cst_per_tonne": 72.0, "cst_per_tonne_km": 0.45835158576386537, "co2_tn": 130.56708}], "LGA_13310": [{"commodity": "Grains", "industry": "grains", "sector": "cropping", "trips_count": 19, "trailer_loads": 82.54345, "tonnes": 2063.5864, "tonne_kms": 454043.66, "tonnes_per_trailer": 25.000002, "avg_trip_distance": 217.49352, "avg_trip_duration": 2.3416247, "total_trip_distance": 15003.039, "total_trip_duration": 161.66798, "total_freight_value": 1031793.0, "trip_transport_costs": 74987.0, "cst_per_tonne": 36.0, "cst_per_tonne_km": 0.16515335738382672, "co2_tn": 37.80143}, {"commodity": "Wool", "industry": "livestock", "sector": "livestock", "trips_count": 10, "trailer_loads": 50.0, "tonnes": 1000.0, "tonne_kms": 158607.3, "tonnes_per_trailer": 20.0, "avg_trip_distance": 155.11903, "avg_trip_duration": 1.6679106, "total_trip_distance": 7581.5386, "total_trip_duration": 81.50364, "total_freight_value": 1500000.0, "trip_transport_costs": 35990.0, "cst_per_tonne": 36.0, "cst_per_tonne_km": 0.22691457044999214, "co2_tn": 17.213278}, {"commodity": "Sheep", "industry": "livestock", "sector": "livestock", "trips_count": 60, "trailer_loads": 384.0, "tonnes": 3840.0, "tonne_kms": 591107.94, "tonnes_per_trailer": 10.0, "avg_trip_distance": 152.88676, "avg_trip_duration": 1.6477219, "total_trip_distance": 56518.98, "total_trip_duration": 609.3331, "total_freight_value": 26880000.0, "trip_transport_costs": 268782.0, "cst_per_tonne": 70.0, "cst_per_tonne_km": 0.4547085699905749, "co2_tn": 128.3606}], "LGA_13340": [{"commodity": "Wheat", "industry": "grains", "sector": "cropping", "trips_count": 6, "trailer_loads": 232.20282, "tonnes": 5805.0723, "tonne_kms": 1253598.9, "tonnes_per_trailer": 24.999998, "avg_trip_distance": 181.75992, "avg_trip_duration": 2.0641806, "total_trip_distance": 42880.37, "total_trip_duration": 488.10828, "total_freight_value": 2380080.0, "trip_transport_costs": 215616.0, "cst_per_tonne": 37.0, "cst_per_tonne_km": 0.17199790279119886, "co2_tn": 106.17132}, {"commodity": "Small Cattle", "industry": "livestock", "sector": "livestock", "trips_count": 7, "trailer_loads": 35.0, "tonnes": 700.0, "tonne_kms": 189860.1, "tonnes_per_trailer": 20.0, "avg_trip_distance": 259.44122, "avg_trip_duration": 2.805966, "total_trip_distance": 9080.443, "total_trip_duration": 98.2088, "total_freight_value": 1508500.0, "trip_transport_costs": 41821.0, "cst_per_tonne": 60.0, "cst_per_tonne_km": 0.22027150995889572, "co2_tn": 20.65051}], "LGA_13450": [{"commodity": "Grains", "industry": "grains", "sector": "cropping", "trips_count": 12, "trailer_loads": 339.5808, "tonnes": 8489.531, "tonne_kms": 2214550.2, "tonnes_per_trailer": 25.000034, "avg_trip_distance": 199.9333, "avg_trip_duration": 2.2627392, "total_trip_distance": 57626.504, "total_trip_duration": 652.02014, "total_freight_value": 4244761.0, "trip_transport_costs": 326585.0, "cst_per_tonne": 38.0, "cst_per_tonne_km": 0.14747235270316172, "co2_tn": 167.72023}], "LGA_13510": [{"commodity": "Canola", "industry": "grains", "sector": "cropping", "trips_count": 6, "trailer_loads": 103.3795, "tonnes": 2584.4893, "tonne_kms": 175373.55, "tonnes_per_trailer": 25.000006, "avg_trip_distance": 60.837708, "avg_trip_duration": 0.740324, "total_trip_distance": 6781.71, "total_trip_duration": 82.95853, "total_freight_value": 1803974.0, "trip_transport_costs": 36974.0, "cst_per_tonne": 14.0, "cst_per_tonne_km": 0.21082892804172385, "co2_tn": 15.733801}, {"commodity": "Wheat", "industry": "grains", "sector": "cropping", "trips_count": 22, "trailer_loads": 658.26354, "tonnes": 16456.59, "tonne_kms": 1085621.5, "tonnes_per_trailer": 25.000021, "avg_trip_distance": 65.33725, "avg_trip_duration": 0.75033855, "total_trip_distance": 41598.98, "total_trip_duration": 476.32816, "total_freight_value": 6747207.0, "trip_transport_costs": 223686.0, "cst_per_tonne": 14.0, "cst_per_tonne_km": 0.20604398024757592, "co2_tn": 94.97657}, {"commodity": "Sheep", "industry": "livestock", "sector": "livestock", "trips_count": 77, "trailer_loads": 480.0, "tonnes": 4800.0, "tonne_kms": 555442.06, "tonnes_per_trailer": 10.0, "avg_trip_distance": 115.027, "avg_trip_duration": 1.2522913, "total_trip_distance": 52706.88, "total_trip_duration": 573.1876, "total_freight_value": 33600000.0, "trip_transport_costs": 259197.0, "cst_per_tonne": 54.0, "cst_per_tonne_km": 0.4666499489887586, "co2_tn": 120.434}], "LGA_13910": [{"commodity": "Boxed Beef", "industry": "meat", "sector": "cold_food", "trips_count": 9, "trailer_loads": 22.008770000000002, "tonnes": 396.15863, "tonne_kms": 6405.8027, "tonnes_per_trailer": 18.00006, "avg_trip_distance": 15.838159, "avg_trip_duration": 0.19731642, "total_trip_distance": 355.87793, "total_trip_duration": 4.5641007, "total_freight_value": 13073210.0, "trip_transport_costs": 3026.0, "cst_per_tonne": 8.0, "cst_per_tonne_km": 0.47240193536949726, "co2_tn": 0.81250674}, {"commodity": "Wheat", "industry": "grains", "sector": "cropping", "trips_count": 84, "trailer_loads": 3195.6750600000023, "tonnes": 79891.97, "tonne_kms": 2080143.0, "tonnes_per_trailer": 24.99999, "avg_trip_distance": 31.928617, "avg_trip_duration": 0.372786, "total_trip_distance": 82088.32, "total_trip_duration": 981.4473, "total_freight_value": 32755677.0, "trip_transport_costs": 560444.0, "cst_per_tonne": 7.0, "cst_per_tonne_km": 0.26942565973395427, "co2_tn": 185.4362}, {"commodity": "Grains", "industry": "grains", "sector": "cropping", "trips_count": 13, "trailer_loads": 941.0537999999999, "tonnes": 23526.361, "tonne_kms": 369575.6, "tonnes_per_trailer": 25.000008, "avg_trip_distance": 25.475391, "avg_trip_duration": 0.29159725, "total_trip_distance": 14783.023, "total_trip_duration": 175.42679, "total_freight_value": 11763180.0, "trip_transport_costs": 122856.0, "cst_per_tonne": 5.0, "cst_per_tonne_km": 0.3324253131940499, "co2_tn": 33.009235}, {"commodity": "Canola", "industry": "grains", "sector": "cropping", "trips_count": 74, "trailer_loads": 1579.11449, "tonnes": 39477.844, "tonne_kms": 1320073.1, "tonnes_per_trailer": 24.999992, "avg_trip_distance": 28.963482, "avg_trip_duration": 0.33227006, "total_trip_distance": 52386.914, "total_trip_duration": 606.4894, "total_freight_value": 27555555.0, "trip_transport_costs": 326951.0, "cst_per_tonne": 8.0, "cst_per_tonne_km": 0.247676255776676, "co2_tn": 117.19708}, {"commodity": "Small Cattle", "industry": "livestock", "sector": "livestock", "trips_count": 6, "trailer_loads": 30.0, "tonnes": 600.0, "tonne_kms": 13998.3, "tonnes_per_trailer": 20.0, "avg_trip_distance": 23.3305, "avg_trip_duration": 0.26272777, "total_trip_distance": 699.915, "total_trip_duration": 7.8818336, "total_freight_value": 1293000.0, "trip_transport_costs": 4897.0, "cst_per_tonne": 8.0, "cst_per_tonne_km": 0.3498318237970998, "co2_tn": 1.548306}, {"commodity": "Large Cattle", "industry": "livestock", "sector": "livestock", "trips_count": 7, "trailer_loads": 110.606, "tonnes": 2433.33, "tonne_kms": 45527.133, "tonnes_per_trailer": 22.000015, "avg_trip_distance": 36.14722, "avg_trip_duration": 0.41945526, "total_trip_distance": 2069.415, "total_trip_duration": 24.832834, "total_freight_value": 15038000.0, "trip_transport_costs": 15965.0, "cst_per_tonne": 7.0, "cst_per_tonne_km": 0.3506765791750558, "co2_tn": 4.623091}, {"commodity": "Household Waste", "industry": "waste", "sector": "waste", "trips_count": 46, "trailer_loads": 993.6000000000007, "tonnes": 9936.0, "tonne_kms": 160332.27, "tonnes_per_trailer": 10.0, "avg_trip_distance": 15.843109, "avg_trip_duration": 0.20976937, "total_trip_distance": 16033.227, "total_trip_duration": 212.2866, "total_freight_value": 993600.0, "trip_transport_costs": 134422.0, "cst_per_tonne": 14.0, "cst_per_tonne_km": 0.8383969304101393, "co2_tn": 36.88379}], "LGA_14300": [{"commodity": "Wheat", "industry": "grains", "sector": "cropping", "trips_count": 11, "trailer_loads": 231.87732, "tonnes": 5796.93, "tonne_kms": 682401.1, "tonnes_per_trailer": 25.000004, "avg_trip_distance": 113.27261, "avg_trip_duration": 1.349441, "total_trip_distance": 26345.95, "total_trip_duration": 310.4764, "total_freight_value": 2376744.0, "trip_transport_costs": 131109.0, "cst_per_tonne": 23.0, "cst_per_tonne_km": 0.19212893528994998, "co2_tn": 60.359592}, {"commodity": "Sheep", "industry": "livestock", "sector": "livestock", "trips_count": 101, "trailer_loads": 618.0, "tonnes": 6180.0, "tonne_kms": 820307.9, "tonnes_per_trailer": 10.0, "avg_trip_distance": 131.41078, "avg_trip_duration": 1.5911539, "total_trip_distance": 77461.375, "total_trip_duration": 938.3626, "total_freight_value": 43260000.0, "trip_transport_costs": 388411.0, "cst_per_tonne": 63.0, "cst_per_tonne_km": 0.4734946568103507, "co2_tn": 181.39775}], "LGA_14400": [{"commodity": "Grains", "industry": "grains", "sector": "cropping", "trips_count": 7, "trailer_loads": 103.68000000000004, "tonnes": 2592.0, "tonne_kms": 782754.5, "tonnes_per_trailer": 25.0, "avg_trip_distance": 301.28796, "avg_trip_duration": 3.3534048, "total_trip_distance": 31310.18, "total_trip_duration": 348.6938, "total_freight_value": 1296000.0, "trip_transport_costs": 141479.0, "cst_per_tonne": 55.0, "cst_per_tonne_km": 0.18074506338673238, "co2_tn": 69.24732}], "LGA_16200": [], "LGA_16950": [{"commodity": "Grains", "industry": "grains", "sector": "cropping", "trips_count": 16, "trailer_loads": 207.3600000000001, "tonnes": 5184.0, "tonne_kms": 1613914.0, "tonnes_per_trailer": 25.0, "avg_trip_distance": 310.36807, "avg_trip_duration": 3.5060081, "total_trip_distance": 64556.56, "total_trip_duration": 729.2497, "total_freight_value": 2592000.0, "trip_transport_costs": 292111.0, "cst_per_tonne": 56.0, "cst_per_tonne_km": 0.1809955717029377, "co2_tn": 142.75452}], "LGA_17350": [{"commodity": "Oats", "industry": "grains", "sector": "cropping", "trips_count": 6, "trailer_loads": 38.17944, "tonnes": 649.04944, "tonne_kms": 60349.094, "tonnes_per_trailer": 16.999979, "avg_trip_distance": 85.064705, "avg_trip_duration": 0.96644276, "total_trip_distance": 3549.9465, "total_trip_duration": 40.23373, "total_freight_value": 210941.0, "trip_transport_costs": 17592.0, "cst_per_tonne": 27.0, "cst_per_tonne_km": 0.2915051686903958, "co2_tn": 7.8466015}, {"commodity": "Barley", "industry": "grains", "sector": "cropping", "trips_count": 8, "trailer_loads": 171.46641999999997, "tonnes": 4286.655, "tonne_kms": 254601.34, "tonnes_per_trailer": 24.999979, "avg_trip_distance": 64.6542, "avg_trip_duration": 0.729394, "total_trip_distance": 8288.3125, "total_trip_duration": 93.63226, "total_freight_value": 1457464.0, "trip_transport_costs": 50049.0, "cst_per_tonne": 12.0, "cst_per_tonne_km": 0.19657790361951277, "co2_tn": 21.243483}, {"commodity": "Wheat", "industry": "grains", "sector": "cropping", "trips_count": 25, "trailer_loads": 1167.0991900000001, "tonnes": 29177.477, "tonne_kms": 2076590.6, "tonnes_per_trailer": 24.999996, "avg_trip_distance": 78.18084, "avg_trip_duration": 0.8836945, "total_trip_distance": 82425.14, "total_trip_duration": 937.49774, "total_freight_value": 11962769.0, "trip_transport_costs": 429932.0, "cst_per_tonne": 15.0, "cst_per_tonne_km": 0.20703749650587877, "co2_tn": 183.91064}, {"commodity": "Small Cattle", "industry": "livestock", "sector": "livestock", "trips_count": 25, "trailer_loads": 135.0, "tonnes": 2700.0, "tonne_kms": 249599.9, "tonnes_per_trailer": 20.0, "avg_trip_distance": 92.41571, "avg_trip_duration": 1.0909629, "total_trip_distance": 12112.712, "total_trip_duration": 143.33414, "total_freight_value": 5818500.0, "trip_transport_costs": 62191.0, "cst_per_tonne": 23.0, "cst_per_tonne_km": 0.24916429830608905, "co2_tn": 27.768614}], "LGA_17640": [{"commodity": "Grains", "industry": "grains", "sector": "cropping", "trips_count": 9, "trailer_loads": 31.53901, "tonnes": 788.4755, "tonne_kms": 112333.125, "tonnes_per_trailer": 25.000004, "avg_trip_distance": 136.70221, "avg_trip_duration": 1.5389924, "total_trip_distance": 4493.325, "total_trip_duration": 50.662666, "total_freight_value": 394238.0, "trip_transport_costs": 21277.0, "cst_per_tonne": 27.0, "cst_per_tonne_km": 0.1894135871855754, "co2_tn": 9.954821}, {"commodity": "Small Cattle", "industry": "livestock", "sector": "livestock", "trips_count": 21, "trailer_loads": 105.0, "tonnes": 2100.0, "tonne_kms": 159516.7, "tonnes_per_trailer": 20.0, "avg_trip_distance": 75.960335, "avg_trip_duration": 0.83479285, "total_trip_distance": 7975.835, "total_trip_duration": 87.65325, "total_freight_value": 4525500.0, "trip_transport_costs": 41520.0, "cst_per_tonne": 20.0, "cst_per_tonne_km": 0.26028819135895254, "co2_tn": 17.682352}], "LGA_17750": [{"commodity": "Hay", "industry": "grains", "sector": "cropping", "trips_count": 7, "trailer_loads": 62.67835000000001, "tonnes": 1441.601, "tonne_kms": 289603.0, "tonnes_per_trailer": 22.999983, "avg_trip_distance": 199.86406, "avg_trip_duration": 2.220058, "total_trip_distance": 12591.436, "total_trip_duration": 139.86365, "total_freight_value": 432480.0, "trip_transport_costs": 58015.0, "cst_per_tonne": 40.0, "cst_per_tonne_km": 0.20032761747601457, "co2_tn": 27.837688}, {"commodity": "Large Cattle", "industry": "livestock", "sector": "livestock", "trips_count": 8, "trailer_loads": 46.969649999999994, "tonnes": 1033.333, "tonne_kms": 160099.52, "tonnes_per_trailer": 22.00002, "avg_trip_distance": 143.54094, "avg_trip_duration": 1.6902783, "total_trip_distance": 7277.251, "total_trip_duration": 86.4948, "total_freight_value": 6386000.0, "trip_transport_costs": 34757.0, "cst_per_tonne": 34.0, "cst_per_tonne_km": 0.21709712636983888, "co2_tn": 16.285517}, {"commodity": "Small Cattle", "industry": "livestock", "sector": "livestock", "trips_count": 14, "trailer_loads": 75.0, "tonnes": 1500.0, "tonne_kms": 246404.3, "tonnes_per_trailer": 20.0, "avg_trip_distance": 155.62721, "avg_trip_duration": 1.8210881, "total_trip_distance": 11549.28, "total_trip_duration": 134.44308, "total_freight_value": 3232500.0, "trip_transport_costs": 56545.0, "cst_per_tonne": 38.0, "cst_per_tonne_km": 0.22947893531178906, "co2_tn": 26.942554}], "LGA_18230": [{"commodity": "Small Cattle", "industry": "livestock", "sector": "livestock", "trips_count": 7, "trailer_loads": 35.0, "tonnes": 700.0, "tonne_kms": 208887.4, "tonnes_per_trailer": 20.0, "avg_trip_distance": 210.45274, "avg_trip_duration": 2.4155936, "total_trip_distance": 7112.6665, "total_trip_duration": 81.638504, "total_freight_value": 1508500.0, "trip_transport_costs": 40081.0, "cst_per_tonne": 57.0, "cst_per_tonne_km": 0.19187794959291019, "co2_tn": 20.951534}, {"commodity": "Sheep", "industry": "livestock", "sector": "livestock", "trips_count": 61, "trailer_loads": 372.0, "tonnes": 3720.0, "tonne_kms": 1055706.1, "tonnes_per_trailer": 10.0, "avg_trip_distance": 210.62662, "avg_trip_duration": 2.4205544, "total_trip_distance": 72210.695, "total_trip_duration": 829.59357, "total_freight_value": 26040000.0, "trip_transport_costs": 407329.0, "cst_per_tonne": 109.0, "cst_per_tonne_km": 0.3858354202560395, "co2_tn": 212.05696}], "LGA_18400": [{"commodity": "Grains", "industry": "grains", "sector": "cropping", "trips_count": 67, "trailer_loads": 243.79360000000008, "tonnes": 6094.8438, "tonne_kms": 1883008.2, "tonnes_per_trailer": 25.000002, "avg_trip_distance": 292.42084, "avg_trip_duration": 3.1154482, "total_trip_distance": 72403.01, "total_trip_duration": 771.6398, "total_freight_value": 3047421.0, "trip_transport_costs": 327985.0, "cst_per_tonne": 54.0, "cst_per_tonne_km": 0.17418146598729553, "co2_tn": 163.36758}, {"commodity": "Sheep", "industry": "livestock", "sector": "livestock", "trips_count": 6, "trailer_loads": 36.0, "tonnes": 360.0, "tonne_kms": 94964.7, "tonnes_per_trailer": 10.0, "avg_trip_distance": 263.79083, "avg_trip_duration": 2.7772279, "total_trip_distance": 9496.47, "total_trip_duration": 99.9802, "total_freight_value": 2520000.0, "trip_transport_costs": 42408.0, "cst_per_tonne": 118.0, "cst_per_tonne_km": 0.4465643721491258, "co2_tn": 20.838495}, {"commodity": "Pigs", "industry": "livestock", "sector": "livestock", "trips_count": 7, "trailer_loads": 46.0, "tonnes": 828.0, "tonne_kms": 251895.94, "tonnes_per_trailer": 18.0, "avg_trip_distance": 264.0469, "avg_trip_duration": 2.8125753, "total_trip_distance": 12045.931, "total_trip_duration": 128.28271, "total_freight_value": 3038760.0, "trip_transport_costs": 57976.0, "cst_per_tonne": 70.0, "cst_per_tonne_km": 0.23015676930391643, "co2_tn": 29.421463}], "LGA_18710": [], "LGA_20830": [{"commodity": "Hay", "industry": "grains", "sector": "cropping", "trips_count": 6, "trailer_loads": 53.72430000000001, "tonnes": 1235.658, "tonne_kms": 876230.4, "tonnes_per_trailer": 22.999983, "avg_trip_distance": 550.70654, "avg_trip_duration": 5.864612, "total_trip_distance": 25701.287, "total_trip_duration": 273.57196, "total_freight_value": 370697.0, "trip_transport_costs": 143380.0, "cst_per_tonne": 116.0, "cst_per_tonne_km": 0.16363233589896378, "co2_tn": 75.1902}, {"commodity": "Sheep", "industry": "livestock", "sector": "livestock", "trips_count": 17, "trailer_loads": 102.0, "tonnes": 1020.0, "tonne_kms": 718712.75, "tonnes_per_trailer": 10.0, "avg_trip_distance": 514.5359, "avg_trip_duration": 5.3928776, "total_trip_distance": 48197.63, "total_trip_duration": 505.23746, "total_freight_value": 7140000.0, "trip_transport_costs": 269233.0, "cst_per_tonne": 264.0, "cst_per_tonne_km": 0.374603772943363, "co2_tn": 141.56247}], "LGA_26670": [{"commodity": "Sheep", "industry": "livestock", "sector": "livestock", "trips_count": 38, "trailer_loads": 228.0, "tonnes": 2280.0, "tonne_kms": 761424.8, "tonnes_per_trailer": 10.0, "avg_trip_distance": 251.38875, "avg_trip_duration": 2.6133804, "total_trip_distance": 54044.445, "total_trip_duration": 561.8991, "total_freight_value": 15960000.0, "trip_transport_costs": 287274.0, "cst_per_tonne": 126.0, "cst_per_tonne_km": 0.3772842096523483, "co2_tn": 151.67099}], "LGA_26810": [{"commodity": "Hay", "industry": "grains", "sector": "cropping", "trips_count": 7, "trailer_loads": 62.67835000000001, "tonnes": 1441.601, "tonne_kms": 1027260.3, "tonnes_per_trailer": 22.999983, "avg_trip_distance": 578.36975, "avg_trip_duration": 6.273394, "total_trip_distance": 29981.654, "total_trip_duration": 325.45297, "total_freight_value": 432480.0, "trip_transport_costs": 168213.0, "cst_per_tonne": 117.0, "cst_per_tonne_km": 0.1637488143523748, "co2_tn": 88.01657}, {"commodity": "Small Cattle", "industry": "livestock", "sector": "livestock", "trips_count": 7, "trailer_loads": 35.0, "tonnes": 700.0, "tonne_kms": 466062.6, "tonnes_per_trailer": 20.0, "avg_trip_distance": 450.15567, "avg_trip_duration": 5.012357, "total_trip_distance": 15755.448, "total_trip_duration": 175.4325, "total_freight_value": 1508500.0, "trip_transport_costs": 89273.0, "cst_per_tonne": 128.0, "cst_per_tonne_km": 0.19154630006109025, "co2_tn": 46.10986}], "LGA_89399": [{"commodity": "Boxed Beef", "industry": "meat", "sector": "cold_food", "trips_count": 12, "trailer_loads": 117.05450999999998, "tonnes": 2106.9827, "tonne_kms": 349167.53, "tonnes_per_trailer": 18.0, "avg_trip_distance": 141.2926, "avg_trip_duration": 1.6325337, "total_trip_distance": 19398.195, "total_trip_duration": 223.75255, "total_freight_value": 69530413.0, "trip_transport_costs": 91567.0, "cst_per_tonne": 43.0, "cst_per_tonne_km": 0.2622441481224293, "co2_tn": 42.981335}]}}